voluptuous_serialize/__init__.py
voluptuous_serialize/py.typed
voluptuous_serialize-2.7.0.dist-info/licenses/LICENSE
voluptuous_serialize-2.7.0.dist-info/METADATA
voluptuous_serialize-2.7.0.dist-info/WHEEL
voluptuous_serialize-2.7.0.dist-info/top_level.txt
voluptuous_serialize-2.7.0.dist-info/RECORD
