Metadata-Version: 2.4
Name: voluptuous-serialize
Version: 2.7.0
Summary: Convert voluptuous schemas to dictionaries
Author-email: Paulus Schoutsen <Paulus@PaulusSchoutsen.nl>
License-Expression: Apache-2.0
Project-URL: Source code, https://github.com/home-assistant-libs/voluptuous-serialize
Requires-Python: >=3.9
License-File: LICENSE
Requires-Dist: voluptuous
Dynamic: license-file
